{
  "data": {
    "nickname": "ABCD",
    "avatar": "https://tse1-mm.cn.bing.net/th/id/R-C.21d5b19e43d805a41cf66e613dab096c?rik=QBQlEJSM%2bHMlgg&riu=http%3a%2f%2f5b0988e595225.cdn.sohucs.com%2fimages%2f20180806%2f8ad4e58b5c684b5b8894fbb4aa282331.jpeg&ehk=PFxfH43wmQtJ1HksB7DIIvnlOrI6UadUbRKjQ9j4K5g%3d&risl=&pid=ImgRaw&r=0",
    "intro": "sdlfs;dlmf;sdlmf;smf;lsmdadfjisnfnhofnsfjfioej",
    "background": "https://tse1-mm.cn.bing.net/th/id/R-C.e262e21897230b32af3205a5e0e25d39?rik=Q5lfPebDpkBg9g&riu=http%3a%2f%2fpic27.nipic.com%2f20130226%2f2786001_104500158000_2.jpg&ehk=xbcr%2fjTu7P72VaFVq4bFcznReik4zPMWa2kIeLWogJA%3d&risl=&pid=ImgRaw&r=0",
    "pubGoods": []
  }
}